{
  "name": "Kilowattrel",
  "korName": "찌리비크군함조포켓몬",
  "species": "군함조포켓몬",
  "imageUrl": "https://img.pokemondb.net/artwork/avif/kilowattrel.avif",
  "types": [
    "Electric",
    "Flying"
  ],
  "baseStats": {
    "hp": 70,
    "attack": 70,
    "defense": 60,
    "spAtk": 105,
    "spDef": 60,
    "speed": 125,
    "total": 490
  },
  "evolutions": [
    {
      "name": "Wattrel",
      "image": "https://img.pokemondb.net/sprites/scarlet-violet/normal/wattrel.png",
      "types": [
        "Electric",
        "Flying"
      ],
      "evolveMethod": "(Level 25)"
    },
    {
      "name": "Kilowattrel",
      "image": "https://img.pokemondb.net/sprites/scarlet-violet/normal/kilowattrel.png",
      "types": [
        "Electric",
        "Flying"
      ]
    }
  ]
}